{
    "mode": "queue",
    "queue": [
    {
      "path": "C:\\src\\SlippiComboRenderer\\src\\ComboRenderer\\slp\\STRONG#3.slp",
      "startFrame": 4900,
      "endFrame": 5517
    },
    {
      "path": "C:\\src\\SlippiComboRenderer\\src\\ComboRenderer\\slp\\JZ#339.slp",
      "startFrame": 6885,
      "endFrame": 7380
    },
    {
      "path": "C:\\src\\SlippiComboRenderer\\src\\ComboRenderer\\slp\\BREN#824-3.slp",
      "startFrame": 5050,
      "endFrame": 5969
    },
    {
      "path": "C:\\src\\SlippiComboRenderer\\src\\ComboRenderer\\slp\\DOBY#705-2.slp",
      "startFrame": 1189,
      "endFrame": 1800
    },
    {
      "path": "C:\\src\\SlippiComboRenderer\\src\\ComboRenderer\\slp\\SATP#173.slp",
      "startFrame": 3670,
      "endFrame": 4400
    },
    {
      "path": "C:\\src\\SlippiComboRenderer\\src\\ComboRenderer\\slp\\YAYA#919.slp",
      "startFrame": 3500,
      "endFrame": 4127
    },
    {
      "path": "C:\\src\\SlippiComboRenderer\\src\\ComboRenderer\\slp\\JOHN#311.slp",
      "startFrame": 7771,
      "endFrame": 8234
    },
    {
      "path": "C:\\src\\SlippiComboRenderer\\src\\ComboRenderer\\slp\\THER#787.slp",
      "startFrame": 540,
      "endFrame": 1016
    },
    {
      "path": "C:\\src\\SlippiComboRenderer\\src\\ComboRenderer\\slp\\THER#787-1.slp",
      "startFrame": 6100,
      "endFrame": 6534
    },
    {
      "path": "C:\\src\\SlippiComboRenderer\\src\\ComboRenderer\\slp\\BREN#824-2.slp",
      "startFrame": 1882,
      "endFrame": 2445
    },
    {
      "path": "C:\\src\\SlippiComboRenderer\\src\\ComboRenderer\\slp\\LPMM#86.slp",
      "startFrame": 2700,
      "endFrame": 3523
    },
    {
      "path": "C:\\src\\SlippiComboRenderer\\src\\ComboRenderer\\slp\\BREN#824-1.slp",
      "startFrame": 610,
      "endFrame": 1274
    },
    {
      "path": "C:\\src\\SlippiComboRenderer\\src\\ComboRenderer\\slp\\ELOC#180.slp",
      "startFrame": 9080,
      "endFrame": 9769
    },
    {
      "path": "C:\\src\\SlippiComboRenderer\\src\\ComboRenderer\\slp\\MILK#338.slp",
      "startFrame": 4583,
      "endFrame": 5838
    },
    {
      "path": "C:\\src\\SlippiComboRenderer\\src\\ComboRenderer\\slp\\CHID#695.slp",
      "startFrame": 4000,
      "endFrame": 4600
    },
    {
      "path": "C:\\src\\SlippiComboRenderer\\src\\ComboRenderer\\slp\\TEA#237.slp",
      "startFrame": 1750,
      "endFrame": 2460
    },
    {
      "path": "C:\\src\\SlippiComboRenderer\\src\\ComboRenderer\\slp\\HOD#492.slp",
      "startFrame": 3762,
      "endFrame": 4237
    },
    {
      "path": "C:\\src\\SlippiComboRenderer\\src\\ComboRenderer\\slp\\DAHL#372-1.slp",
      "startFrame": 8286,
      "endFrame": 8700
    },
    {
      "path": "C:\\src\\SlippiComboRenderer\\src\\ComboRenderer\\slp\\DAHL#372-2.slp",
      "startFrame": 8164,
      "endFrame": 8670
    },
    {
      "path": "C:\\src\\SlippiComboRenderer\\src\\ComboRenderer\\slp\\TOMA#783.slp",
      "startFrame": 6813,
      "endFrame": 7400
    },
    {
      "path": "C:\\src\\SlippiComboRenderer\\src\\ComboRenderer\\slp\\SILVI#0.slp",
      "startFrame": 11410,
      "endFrame": 12227
    },
    {
        "path": "C:\\src\\SlippiComboRenderer\\src\\ComboRenderer\\slp\\DERRICK#0.slp",
        "startFrame": 4800,
        "endFrame": 5294
    },
    {
        "path":"C:\\src\\SlippiComboRenderer\\src\\ComboRenderer\\slp\\CHID#695-2.slp",
        "startFrame": 3359,
        "endFrame": 3827
    },
    {
        "path": "C:\\src\\SlippiComboRenderer\\src\\ComboRenderer\\slp\\SWID#197.slp",
        "startFrame": 5714,
        "endFrame": 6297
    },
    {
        "path": "C:\\src\\SlippiComboRenderer\\src\\ComboRenderer\\slp\\VALK#839.slp",
        "startFrame": 3739,
        "endFrame": 4206
    },
    {
        "path": "C:\\src\\SlippiComboRenderer\\src\\ComboRenderer\\slp\\CAM#930.slp",
        "startFrame": 3130,
        "endFrame": 3390
    },
    {
        "path": "C:\\src\\SlippiComboRenderer\\src\\ComboRenderer\\slp\\KVD#432.slp",
        "startFrame": 5537,
        "endFrame": 6055
    },
    {
        "path": "C:\\src\\SlippiComboRenderer\\src\\ComboRenderer\\slp\\SILVI#0-2.slp",
        "startFrame": 2489,
        "endFrame": 3116
    },
    {
        "path": "C:\\src\\SlippiComboRenderer\\src\\ComboRenderer\\slp\\INDI#794.slp",
        "startFrame": 7483,
        "endFrame": 7752
    },
    {
        "path": "C:\\src\\SlippiComboRenderer\\src\\ComboRenderer\\slp\\FOUR#862.slp",
        "startFrame": 2292,
        "endFrame": 3300
    },
    {
        "path": "C:\\src\\SlippiComboRenderer\\src\\ComboRenderer\\slp\\BIO#0.slp",
        "startFrame": 9990,
        "endFrame": 10272
    },
    {
        "path": "C:\\src\\SlippiComboRenderer\\src\\ComboRenderer\\slp\\JETS#0.slp",
        "startFrame": 6829,
        "endFrame": 7292
    },
    {
      "path": "C:\\src\\SlippiComboRenderer\\src\\ComboRenderer\\slp\\DOBY#705-1.slp",
      "startFrame": 7500,
      "endFrame": 8182
    },
    {
      "path": "C:\\src\\SlippiComboRenderer\\src\\ComboRenderer\\slp\\KITE#0.slp",
      "startFrame": 5769,
      "endFrame": 6740
    },
    {
      "path": "C:\\src\\SlippiComboRenderer\\src\\ComboRenderer\\slp\\BOSS#832.slp",
      "startFrame": 2136,
      "endFrame": 2985
    },
    {
      "path": "C:\\src\\SlippiComboRenderer\\src\\ComboRenderer\\slp\\SALT#348.slp",
      "startFrame": -100,
      "endFrame": 635
    }
  ]
}